imgrit/__init__.py
imgrit/imgrit.py
imgrit-0.2.0.dist-info/METADATA
imgrit-0.2.0.dist-info/WHEEL
imgrit-0.2.0.dist-info/licenses/LICENSE
imgrit-0.2.0.dist-info/RECORD
